[{"_id":"65892df69efc9fb3c9fc455c","university_id":"002","program_id":"10020101500201A","project_id":"A0100","project_name_th":"ช้างเผือก","type":"1_2567","receive_student_number":15,"only_formal":1,"only_international":1,"only_vocational":1,"only_non_formal":1,"only_ged":1,"description":"คณะเกษตร วท.บ. สาขาวิชาการจัดการศัตรูพืชและสัตว์ (ภาษาไทย ปกติ)","condition":"","interview_location":"มหาวิทยาลัยเกษตรศาสตร์","interview_date":"","interview_time":"","link":"https://admission.ku.ac.th/","grad_current":false,"t_score":false,"created_at":"2023-12-25T07:23:34.048Z","min_total_score":0,"scores":{}},{"_id":"65892df69efc9fb3c9fc45cc","university_id":"002","program_id":"10020101500201A","project_id":"A0200","project_name_th":"เรียนล่วงหน้า","type":"1_2567","receive_student_number":1,"only_formal":1,"only_international":1,"only_vocational":1,"only_non_formal":1,"only_ged":1,"description":"คณะเกษตร วท.บ. สาขาวิชาการจัดการศัตรูพืชและสัตว์ (ภาษาไทย ปกติ)","condition":"","interview_location":"มหาวิทยาลัยเกษตรศาสตร์","interview_date":"","interview_time":"","link":"https://admission.ku.ac.th/","grad_current":false,"t_score":false,"created_at":"2023-12-25T07:23:34.129Z","min_total_score":0,"scores":{}},{"_id":"65892df69efc9fb3c9fc47cb","university_id":"002","program_id":"10020101500201A","project_id":"B1100","project_name_th":"นักเรียนดีเด่นจากโรงเรียนสาธิตแห่ง มก.","type":"2_2567","receive_student_number":1,"only_formal":1,"only_international":1,"only_vocational":1,"only_non_formal":1,"only_ged":1,"description":"คณะเกษตร วท.บ. สาขาวิชาการจัดการศัตรูพืชและสัตว์ (ภาษาไทย ปกติ)","condition":"","interview_location":"มหาวิทยาลัยเกษตรศาสตร์","interview_date":"","interview_time":"","link":"https://admission.ku.ac.th/","grad_current":false,"t_score":false,"created_at":"2023-12-25T07:23:34.347Z","min_total_score":0,"scores":{}},{"_id":"65892df69efc9fb3c9fc488f","university_id":"002","program_id":"10020101500201A","project_id":"B1200","project_name_th":"เมล็ดพันธุ์สู่ศาสตร์แห่งแผ่นดิน","type":"2_2567","receive_student_number":2,"only_formal":1,"only_international":1,"only_vocational":1,"only_non_formal":1,"only_ged":1,"description":"คณะเกษตร วท.บ. สาขาวิชาการจัดการศัตรูพืชและสัตว์ (ภาษาไทย ปกติ)","condition":"","interview_location":"มหาวิทยาลัยเกษตรศาสตร์","interview_date":"","interview_time":"","link":"https://admission.ku.ac.th/","grad_current":false,"t_score":false,"created_at":"2023-12-25T07:23:34.430Z","min_total_score":0,"scores":{}},{"_id":"65892df69efc9fb3c9fc4967","university_id":"002","program_id":"10020101500201A","project_id":"B1600","project_name_th":"โควตาพิเศษ 30 จังหวัด","type":"2_2567","receive_student_number":20,"only_formal":1,"only_international":1,"only_vocational":1,"only_non_formal":1,"only_ged":1,"description":"คณะเกษตร วท.บ. สาขาวิชาการจัดการศัตรูพืชและสัตว์ (ภาษาไทย ปกติ)","condition":"","interview_location":"มหาวิทยาลัยเกษตรศาสตร์","interview_date":"","interview_time":"","link":"https://admission.ku.ac.th/","grad_current":false,"t_score":false,"created_at":"2023-12-25T07:23:34.626Z","min_total_score":0,"scores":{},"score_conditions":{}},{"_id":"65892df69efc9fb3c9fc49d3","university_id":"002","program_id":"10020101500201A","project_id":"B1700","project_name_th":"โควตานักกีฬา","type":"2_2567","receive_student_number":1,"only_formal":1,"only_international":1,"only_vocational":1,"only_non_formal":1,"only_ged":1,"description":"คณะเกษตร วท.บ. สาขาวิชาการจัดการศัตรูพืชและสัตว์ (ภาษาไทย ปกติ)","condition":"","interview_location":"มหาวิทยาลัยเกษตรศาสตร์","interview_date":"","interview_time":"","link":"https://admission.ku.ac.th/","grad_current":false,"t_score":false,"created_at":"2023-12-25T07:23:34.651Z","min_total_score":0,"scores":{}},{"_id":"65892df69efc9fb3c9fc49fc","university_id":"002","program_id":"10020101500201A","project_id":"B1800","project_name_th":"โควตาศิลปวัฒนธรรม","type":"2_2567","receive_student_number":1,"only_formal":1,"only_international":1,"only_vocational":1,"only_non_formal":1,"only_ged":1,"description":"คณะเกษตร วท.บ. สาขาวิชาการจัดการศัตรูพืชและสัตว์ (ภาษาไทย ปกติ)","condition":"","interview_location":"มหาวิทยาลัยเกษตรศาสตร์","interview_date":"","interview_time":"","link":"https://admission.ku.ac.th/","grad_current":false,"t_score":false,"created_at":"2023-12-25T07:23:34.657Z","min_total_score":0,"scores":{}},{"_id":"65892df69efc9fb3c9fc4b59","university_id":"002","program_id":"10020101500201A","project_id":"C2800","project_name_th":"Admission","type":"3_2567","receive_student_number":25,"only_formal":1,"only_international":2,"only_vocational":2,"only_non_formal":2,"only_ged":2,"description":"คณะเกษตร วท.บ. สาขาวิชาการจัดการศัตรูพืชและสัตว์ (ภาษาไทย ปกติ)","condition":"","interview_location":"มหาวิทยาลัยเกษตรศาสตร์","interview_date":"","interview_time":"","link":"https://admission.ku.ac.th/","grad_current":false,"t_score":false,"min_credit_gpa22":12,"min_credit_gpa23":22,"score_conditions":{"min_tgat":1,"min_tpat3":1},"created_at":"2023-12-25T07:23:34.763Z","min_total_score":0,"scores":{"tgat":40,"tpat3":60}},{"_id":"6655959ee5b2e99524b8524c","university_id":"002","program_id":"10020101500201A","project_id":"D3100","project_name_th":"รับตรงอิสระ","type":"41_2567","receive_student_number":5,"only_formal":1,"only_international":1,"only_vocational":1,"only_non_formal":1,"only_ged":1,"description":"คณะเกษตร วท.บ. สาขาวิชาการจัดการศัตรูพืชและสัตว์ (ภาษาไทย ปกติ)","condition":"","interview_location":"มหาวิทยาลัยเกษตรศาสตร์","interview_date":"","interview_time":"","link":"https://admission.ku.ac.th/","grad_current":false,"t_score":false,"created_at":"2024-05-28T08:28:14.460Z","score_conditions":{}}]