[{"_id":"651bb18f5a0467ea168e30dd","university_id":"164","program_id":"21640101700801A","type":"1_2567","receive_student_number":40,"only_formal":1,"only_international":1,"only_vocational":1,"only_non_formal":1,"only_ged":1,"description":"หลักสูตรครุศาสตรบัณฑิต สาขาวิชาคณิตศาสตร์ 4 ปี คณะครุศาสตร์","condition":"คุณสมบัติของผู้สมัคร : ม.6 กลุ่มสาระคณิตศาสตร์ ไม่น้อยกว่า 15 หน่วยกิต เกณฑ์พิจารณา : GPAX (ไม่ต่ำกว่า 2.50) = 10% ,TGAT (ความถนัดทั่วไป) = 10%, TPAT5 (ความถนัดด้านครุศาสตร์/ศึกษาศาสตร์) = 60% และแฟ้มสะสมผลงาน (Portfolio) ที่เกี่ยวกับคณิตศาสตร์ = 20%","interview_location":"รายละเอียดจะประกาศให้ทราบอีกครั้งผ่านทางเว็บไซต์: http://regis.skru.ac.th/skru_app/","interview_date":"ช่วงเดือน พย. 66 - มค. 67","interview_time":"0900-1200 น.","link":"http://regis.skru.ac.th/skru_app","grad_current":false,"t_score":false,"min_gpax":2.5,"score_conditions":{"min_gpax":2.5},"created_at":"2023-10-03T06:15:43.199Z"},{"_id":"651bb18f5a0467ea168e30de","university_id":"164","program_id":"21640101700801A","type":"2_2567","receive_student_number":27,"only_formal":1,"only_international":1,"only_vocational":1,"only_non_formal":1,"only_ged":1,"description":"หลักสูตรครุศาสตรบัณฑิต สาขาวิชาคณิตศาสตร์ 4 ปี คณะครุศาสตร์","condition":"คุณสมบัติของผู้สมัคร : ม.6 กลุ่มสาระคณิตศาสตร์ ไม่น้อยกว่า 15 หน่วยกิต เกณฑ์พิจารณา : GPAX (ไม่ต่ำกว่า 2.50) = 20% ,TPAT5 (ความถนัดด้านครุศาสตร์/ศึกษาศาสตร์) = 40% และแฟ้มสะสมผลงาน (Portfolio) ที่เกี่ยวข้องกับคณิตศาสตร์ = 40%","interview_location":"รายละเอียดจะประกาศให้ทราบอีกครั้งผ่านทางเว็บไซต์: http://regis.skru.ac.th/skru_app/","interview_date":"ช่วงเดือน มีค. - เมย. 67","interview_time":"0900-1200 น.","link":"http://regis.skru.ac.th/skru_app","grad_current":false,"t_score":false,"min_gpax":2.5,"score_conditions":{"min_gpax":2.5},"created_at":"2023-10-03T06:15:43.201Z"},{"_id":"651bb18f5a0467ea168e30df","university_id":"164","program_id":"21640101700801A","type":"3_2567","receive_student_number":24,"only_formal":1,"only_international":1,"only_vocational":1,"only_non_formal":1,"only_ged":1,"description":"หลักสูตรครุศาสตรบัณฑิต สาขาวิชาคณิตศาสตร์ 4 ปี คณะครุศาสตร์","condition":"คุณสมบัติของผู้สมัคร : ม.6 กลุ่มสาระคณิตศาสตร์ ไม่น้อยกว่า 15 หน่วยกิต เกณฑ์พิจารณา : GPAX (ไม่ต่ำกว่า 2.50) = 10% ,TGAT (ความถนัดทั่วไป) = 10%, TPAT5 (ความถนัดด้านครุศาสตร์/ศึกษาศาสตร์) = 20% และ A-Level คณิตศาสตร์ = 60% ","interview_location":"รายละเอียดจะประกาศให้ทราบอีกครั้งผ่านทางเว็บไซต์: http://regis.skru.ac.th/skru_app/","interview_date":"ช่วงเดือน พค. - มิย. 67","interview_time":"0900-1200 น.","link":"http://regis.skru.ac.th/skru_app","grad_current":false,"t_score":false,"min_gpax":2.5,"min_credit_gpa22":15,"score_conditions":{"min_gpax":2.5},"created_at":"2023-10-03T06:15:43.201Z","min_total_score":0,"scores":{"gpax":10,"tgat":10,"tpat5":20,"a_lv_61":60}}]