[{"_id":"6533ddefb1380a1fd9e2af27","university_id":"192","program_id":"31920105620201A","type":"1_2567","receive_student_number":40,"only_formal":1,"only_international":2,"only_vocational":2,"only_non_formal":2,"only_ged":2,"description":"บริหารธุรกิจบัณฑิต (ธุรกิจการบิน)","link":"https://admission.rmutk.ac.th","grad_current":false,"t_score":false,"min_gpax":2,"score_conditions":{"min_gpax":2},"created_at":"2023-10-21T14:19:27.969Z","min_total_score":0,"scores":{}},{"_id":"6533ddf0b1380a1fd9e2af65","university_id":"192","program_id":"31920105620201A","type":"2_2567","receive_student_number":8,"only_formal":1,"only_international":2,"only_vocational":2,"only_non_formal":2,"only_ged":2,"description":"บริหารธุรกิจบัณฑิต (ธุรกิจการบิน)","link":"https://admission.rmutk.ac.th","grad_current":false,"t_score":false,"min_gpax":2,"score_conditions":{"min_gpax":2},"created_at":"2023-10-21T14:19:28.127Z","min_total_score":0,"scores":{}},{"_id":"6533ddf0b1380a1fd9e2afa3","university_id":"192","program_id":"31920105620201A","type":"3_2567","receive_student_number":20,"only_formal":1,"only_international":2,"only_vocational":2,"only_non_formal":2,"only_ged":2,"description":"บริหารธุรกิจบัณฑิต (ธุรกิจการบิน)","link":"https://admission.rmutk.ac.th","grad_current":false,"t_score":false,"min_gpax":2,"score_conditions":{"min_gpax":2},"created_at":"2023-10-21T14:19:28.149Z","min_total_score":0,"scores":{"tgat":30,"tgat1":20,"tgat2":30,"tgat3":20}},{"_id":"666335e7cb75d783760ff540","university_id":"192","program_id":"31920105620201A","type":"42_2567","receive_student_number":20,"only_formal":1,"only_international":2,"only_vocational":2,"only_non_formal":2,"only_ged":2,"description":"บริหารธุรกิจบัณฑิต (ธุรกิจการบิน)","link":"https://admission.rmutk.ac.th","grad_current":false,"t_score":false,"min_gpax":2,"score_conditions":{"min_gpax":2},"created_at":"2024-06-07T16:31:35.603Z"}]