[{"program_id":"10150104212703B","project_id":"C0001","major_id":"C","program_name_th":"วท.บ.ฟิสิกส์อุตสาหกรรมและอุปกรณ์การแพทย์","program_type_name_th":"ภาษาไทย พิเศษ","major_name_th":"กลุ่มวิชาอุปกรณ์การแพทย์","project_name_th":"การคัดเลือกผ่านระบบกลาง Admissions","min_score":35.305,"max_score":51.208,"min_score_ds":35.305,"max_score_ds":51.208,"est_min_score_mean":32.1205,"est_min_score_mean_sd":33.2201,"est_min_score_regression":32.9176,"receive_student_number":30,"scores":{"tgat":50,"tpat3":50}}]