[{"program_id":"10170103500402E","project_id":"A3301","major_id":"0","program_name_th":"ผู้ประกอบการเกษตรเชิงนวัตกรรม (หลักสูตรนานาชาติ)","program_type_name_th":"นานาชาติ","major_name_th":"0","project_name_th":"สำนักวิชาเทคโนโลยีการเกษตร (สาขาวิชาผู้ประกอบการเกษตรเชิงนวัตกรรม(หลักสูตรนานาชาติ)","min_score":48.75,"max_score":48.75,"min_score_ds":48.75,"max_score_ds":48.75,"est_min_score_mean":44.822,"est_min_score_mean_sd":44.822,"est_min_score_regression":44.9199,"receive_student_number":30,"scores":{"cal_type":"1","cal_score_sum":100,"cal_subject_name":"a_lv_82"}}]