[{"program_id":"10190111302101A","project_id":"J0010","major_id":"0","program_name_th":"หลักสูตรวิศวกรรมศาสตรบัณฑิต (วศ.บ.) สาขาวิชาวิศวกรรมโยธา ภาคปกติ","program_type_name_th":"ภาษาไทย ปกติ","major_name_th":"0","project_name_th":"Admission ","min_score":38.9042,"max_score":47.9915,"min_score_ds":38.5247,"max_score_ds":47.0872,"est_min_score_mean":36.5592,"est_min_score_mean_sd":37.5868,"est_min_score_regression":36.5592,"receive_student_number":70,"scores":{"gpax":10,"tgat":15,"tpat3":25,"a_lv_61":25,"a_lv_64":25}}]