[{"program_id":"21640103700901A","project_id":"A0001","major_id":"0","program_name_th":"ค.บ. คอมพิวเตอร์ศึกษา","program_type_name_th":"ภาษาไทย ปกติ","major_name_th":"0","project_name_th":"เกณฑ์การคัดเลือกรูปแบบที่ 1","min_score":43.208,"max_score":58.319,"min_score_ds":27.2775,"max_score_ds":58.319,"est_min_score_mean":27.4525,"est_min_score_mean_sd":28.6277,"est_min_score_regression":25.2515,"receive_student_number":10,"scores":{"tgat":50,"tpat5":50}},{"program_id":"21640103700901A","project_id":"A0002","major_id":"0","program_name_th":"ค.บ. คอมพิวเตอร์ศึกษา","program_type_name_th":"ภาษาไทย ปกติ","major_name_th":"0","project_name_th":"เกณฑ์การคัดเลือกรูปแบบที่ 2","min_score":60.5,"max_score":60.5,"min_score_ds":60.5,"max_score_ds":60.5,"est_min_score_mean":60.9708,"est_min_score_mean_sd":62.0293,"est_min_score_regression":60.9708,"receive_student_number":1,"scores":{"gpax":10,"tgat":50,"tpat5":40}}]